{
  "batch_id": "batch-002",
  "injected_errors": [
    {
      "error_id": "batch-002-001",
      "cycle_id": "batch-002",
      "type": "duplicate_record",
      "dataset": "payments",
      "severity": "medium",
      "row_index": 2,
      "column": null,
      "message": "A duplicate record was appended.",
      "original_value": null,
      "dirty_value": null
    },
    {
      "error_id": "batch-002-002",
      "cycle_id": "batch-002",
      "type": "freight_outlier",
      "dataset": "delivery",
      "severity": "low",
      "row_index": 12,
      "column": "freight_value",
      "message": "Freight value was changed to an unrealistic outlier.",
      "original_value": "16.46",
      "dirty_value": "99999.99"
    },
    {
      "error_id": "batch-002-003",
      "cycle_id": "batch-002",
      "type": "orphan_record",
      "dataset": "delivery",
      "severity": "high",
      "row_index": 2,
      "column": "order_id",
      "message": "Foreign key no longer matches a clean order.",
      "original_value": "6514b8ad8028c9f2cc2374ded245783f",
      "dirty_value": "orphan-3683"
    },
    {
      "error_id": "batch-002-004",
      "cycle_id": "batch-002",
      "type": "null_key",
      "dataset": "payments",
      "severity": "critical",
      "row_index": 1,
      "column": "order_id",
      "message": "Primary key order_id was blanked out.",
      "original_value": "a4591c265e18cb1dcee52889e2d8acc3",
      "dirty_value": ""
    },
    {
      "error_id": "batch-002-005",
      "cycle_id": "batch-002",
      "type": "missing_column",
      "dataset": "payments",
      "severity": "high",
      "row_index": null,
      "column": "payment_value",
      "message": "A required column was removed from the dataset.",
      "original_value": null,
      "dirty_value": null
    }
  ]
}